{
  "generated_at": "2026-06-13T23:08:56.493680+00:00",
  "as_of_date": "2026-06-13",
  "model_version": "v7-baseline-0.2.0",
  "league_hr_per_pa": 0.035866780529461996,
  "tier": "primary",
  "ev_threshold_pct_min": 25.0,
  "ev_threshold_pct_max": null,
  "ev_threshold_pct": 25.0,
  "total_games_today": 15,
  "games_pregame": 3,
  "games_excluded_live_or_complete": 12,
  "picks": [
    {
      "tier": "primary",
      "daily_rank": 14,
      "batter": "James Wood",
      "batter_id": 695578,
      "batter_hand": "L",
      "team": "WSH",
      "lineup_spot": 1,
      "pitcher": "Luis Castillo",
      "pitcher_id": 622491,
      "pitcher_hand": "R",
      "park": "WSH",
      "game_pk": 822725,
      "game_datetime": "2026-06-13T20:05:00+00:00",
      "line": 0.5,
      "fd_odds": 270,
      "dk_odds": 284,
      "best_book": "draftkings",
      "market_prob_devig": 0.2574,
      "devig_method": "single_sided",
      "devig_inputs": {},
      "model_prob": 0.3841,
      "ev_pct": 47.49,
      "edge_pct": 12.67,
      "blended_hr_per_pa": 0.05274,
      "breakout_score": 0.15,
      "low_confidence": false,
      "pitcher_factor_shrunk": true,
      "trend_signal": -0.0415,
      "unstable_recent": false,
      "top_3_features": [
        {
          "name": "batter_skill",
          "value": 1.5694,
          "deviation": 0.5694
        },
        {
          "name": "pitcher",
          "value": 1.5395,
          "deviation": 0.5395
        },
        {
          "name": "temperature",
          "value": 1.2,
          "deviation": 0.2
        }
      ],
      "tier_rank": 6,
      "stacked": true,
      "stacked_with": [
        "CJ Abrams",
        "Daylen Lile",
        "Luis Garc\u00eda Jr."
      ],
      "filter_status": {
        "passes_baseline": true,
        "passes_triple": true,
        "passes_quad": true,
        "passes_anchor": false
      }
    },
    {
      "tier": "primary",
      "daily_rank": 15,
      "batter": "Gavin Sheets",
      "batter_id": 657757,
      "batter_hand": "L",
      "team": "SD",
      "lineup_spot": 5,
      "pitcher": "Trey Gibson",
      "pitcher_id": 694346,
      "pitcher_hand": "R",
      "park": "BAL",
      "game_pk": 824828,
      "game_datetime": "2026-06-13T20:05:00+00:00",
      "line": 0.5,
      "fd_odds": 440,
      "dk_odds": 438,
      "best_book": "fanduel",
      "market_prob_devig": 0.1763,
      "devig_method": "single_sided",
      "devig_inputs": {},
      "model_prob": 0.2667,
      "ev_pct": 44.0,
      "edge_pct": 9.04,
      "blended_hr_per_pa": 0.05052,
      "breakout_score": -0.0552,
      "low_confidence": false,
      "pitcher_factor_shrunk": true,
      "trend_signal": -0.3242,
      "unstable_recent": false,
      "top_3_features": [
        {
          "name": "batter_skill",
          "value": 1.5033,
          "deviation": 0.5033
        },
        {
          "name": "temperature",
          "value": 1.2,
          "deviation": 0.2
        },
        {
          "name": "park",
          "value": 1.1545,
          "deviation": 0.1545
        }
      ],
      "tier_rank": 12,
      "stacked": false,
      "stacked_with": [],
      "filter_status": {
        "passes_baseline": true,
        "passes_triple": true,
        "passes_quad": true,
        "passes_anchor": true
      }
    },
    {
      "tier": "primary",
      "daily_rank": 13,
      "batter": "Michael Harris II",
      "batter_id": 671739,
      "batter_hand": "L",
      "team": "ATL",
      "lineup_spot": 2,
      "pitcher": "Sean Manaea",
      "pitcher_id": 640455,
      "pitcher_hand": "L",
      "park": "NYM",
      "game_pk": 823616,
      "game_datetime": "2026-06-13T20:10:00+00:00",
      "line": 0.5,
      "fd_odds": 440,
      "dk_odds": 527,
      "best_book": "draftkings",
      "market_prob_devig": 0.1637,
      "devig_method": "single_sided",
      "devig_inputs": {},
      "model_prob": 0.239,
      "ev_pct": 49.85,
      "edge_pct": 7.53,
      "blended_hr_per_pa": 0.042,
      "breakout_score": 0.15,
      "low_confidence": false,
      "pitcher_factor_shrunk": true,
      "trend_signal": -0.1266,
      "unstable_recent": false,
      "top_3_features": [
        {
          "name": "batter_skill",
          "value": 1.3551,
          "deviation": 0.3551
        },
        {
          "name": "temperature",
          "value": 1.189,
          "deviation": 0.189
        },
        {
          "name": "breakout_signal",
          "value": 1.15,
          "deviation": 0.15
        }
      ],
      "tier_rank": 14,
      "stacked": true,
      "stacked_with": [
        "Matt Olson",
        "Eli White"
      ],
      "filter_status": {
        "passes_baseline": true,
        "passes_triple": true,
        "passes_quad": false,
        "passes_anchor": false
      }
    },
    {
      "tier": "primary",
      "daily_rank": 18,
      "batter": "Jahmai Jones",
      "batter_id": 663330,
      "batter_hand": "R",
      "team": "DET",
      "lineup_spot": 6,
      "pitcher": "Joey Cantillo",
      "pitcher_id": 676282,
      "pitcher_hand": "L",
      "park": "CLE",
      "game_pk": 824426,
      "game_datetime": "2026-06-13T20:10:00+00:00",
      "line": 0.5,
      "fd_odds": 610,
      "dk_odds": 630,
      "best_book": "draftkings",
      "market_prob_devig": 0.132,
      "devig_method": "single_sided",
      "devig_inputs": {},
      "model_prob": 0.1939,
      "ev_pct": 41.53,
      "edge_pct": 6.19,
      "blended_hr_per_pa": 0.03618,
      "breakout_score": -0.0358,
      "low_confidence": false,
      "pitcher_factor_shrunk": false,
      "trend_signal": -1.0,
      "unstable_recent": true,
      "top_3_features": [
        {
          "name": "pitcher",
          "value": 1.6,
          "deviation": 0.6
        },
        {
          "name": "park",
          "value": 0.7897,
          "deviation": 0.2103
        },
        {
          "name": "batter_skill",
          "value": 1.1673,
          "deviation": 0.1673
        }
      ],
      "tier_rank": 16,
      "stacked": true,
      "stacked_with": [
        "Dillon Dingler",
        "Spencer Torkelson",
        "Wenceel P\u00e9rez"
      ],
      "filter_status": {
        "passes_baseline": true,
        "passes_triple": true,
        "passes_quad": false,
        "passes_anchor": true
      }
    },
    {
      "tier": "primary",
      "daily_rank": 19,
      "batter": "Eli White",
      "batter_id": 642201,
      "batter_hand": "R",
      "team": "ATL",
      "lineup_spot": 6,
      "pitcher": "Sean Manaea",
      "pitcher_id": 640455,
      "pitcher_hand": "L",
      "park": "NYM",
      "game_pk": 823616,
      "game_datetime": "2026-06-13T20:10:00+00:00",
      "line": 0.5,
      "fd_odds": 680,
      "dk_odds": 670,
      "best_book": "fanduel",
      "market_prob_devig": 0.1226,
      "devig_method": "single_sided",
      "devig_inputs": {},
      "model_prob": 0.1787,
      "ev_pct": 39.39,
      "edge_pct": 5.61,
      "blended_hr_per_pa": 0.03595,
      "breakout_score": 0.0269,
      "low_confidence": false,
      "pitcher_factor_shrunk": true,
      "trend_signal": 0.0615,
      "unstable_recent": false,
      "top_3_features": [
        {
          "name": "temperature",
          "value": 1.189,
          "deviation": 0.189
        },
        {
          "name": "batter_skill",
          "value": 1.1601,
          "deviation": 0.1601
        },
        {
          "name": "wind",
          "value": 1.0749,
          "deviation": 0.0749
        }
      ],
      "tier_rank": 19,
      "stacked": true,
      "stacked_with": [
        "Matt Olson",
        "Michael Harris II"
      ],
      "filter_status": {
        "passes_baseline": true,
        "passes_triple": true,
        "passes_quad": false,
        "passes_anchor": true
      }
    },
    {
      "tier": "primary",
      "daily_rank": 22,
      "batter": "Ryan O'Hearn",
      "batter_id": 656811,
      "batter_hand": "L",
      "team": "PIT",
      "lineup_spot": 4,
      "pitcher": "Lake Bachar",
      "pitcher_id": 669199,
      "pitcher_hand": "R",
      "park": "PIT",
      "game_pk": 823369,
      "game_datetime": "2026-06-13T20:05:00+00:00",
      "line": 0.5,
      "fd_odds": 630,
      "dk_odds": 589,
      "best_book": "fanduel",
      "market_prob_devig": 0.134,
      "devig_method": "single_sided",
      "devig_inputs": {},
      "model_prob": 0.1843,
      "ev_pct": 34.57,
      "edge_pct": 5.03,
      "blended_hr_per_pa": 0.03941,
      "breakout_score": 0.0786,
      "low_confidence": false,
      "pitcher_factor_shrunk": true,
      "trend_signal": -0.2656,
      "unstable_recent": false,
      "top_3_features": [
        {
          "name": "batter_skill",
          "value": 1.2716,
          "deviation": 0.2716
        },
        {
          "name": "temperature",
          "value": 1.155,
          "deviation": 0.155
        },
        {
          "name": "pitcher",
          "value": 0.9114,
          "deviation": 0.0886
        }
      ],
      "tier_rank": 20,
      "stacked": false,
      "stacked_with": [],
      "filter_status": {
        "passes_baseline": true,
        "passes_triple": true,
        "passes_quad": false,
        "passes_anchor": true
      }
    },
    {
      "tier": "primary",
      "daily_rank": 28,
      "batter": "Colson Montgomery",
      "batter_id": 695657,
      "batter_hand": "L",
      "team": "CHW",
      "lineup_spot": 4,
      "pitcher": "Yoshinobu Yamamoto",
      "pitcher_id": 808967,
      "pitcher_hand": "R",
      "park": "CHW",
      "game_pk": 824587,
      "game_datetime": "2026-06-13T20:10:00+00:00",
      "line": 0.5,
      "fd_odds": 490,
      "dk_odds": 536,
      "best_book": "draftkings",
      "market_prob_devig": 0.1552,
      "devig_method": "single_sided",
      "devig_inputs": {},
      "model_prob": 0.2046,
      "ev_pct": 30.13,
      "edge_pct": 4.94,
      "blended_hr_per_pa": 0.05963,
      "breakout_score": -0.0792,
      "low_confidence": false,
      "pitcher_factor_shrunk": true,
      "trend_signal": -0.1529,
      "unstable_recent": false,
      "top_3_features": [
        {
          "name": "batter_skill",
          "value": 1.924,
          "deviation": 0.924
        },
        {
          "name": "pitcher",
          "value": 0.7124,
          "deviation": 0.2876
        },
        {
          "name": "wind",
          "value": 1.1525,
          "deviation": 0.1525
        }
      ],
      "tier_rank": 21,
      "stacked": false,
      "stacked_with": [],
      "filter_status": {
        "passes_baseline": true,
        "passes_triple": true,
        "passes_quad": false,
        "passes_anchor": true
      }
    }
  ],
  "skipped_count": 5,
  "skipped_reference": "data/processed/skipped_batters_2026-06-13.json"
}